loppers/__init__.py
loppers/cli.py
loppers/extensions.py
loppers/ignore_patterns.py
loppers/loppers.py
loppers/mapping.py
loppers/source_utils.py
loppers-2.3.0.dist-info/METADATA
loppers-2.3.0.dist-info/WHEEL
loppers-2.3.0.dist-info/entry_points.txt
loppers-2.3.0.dist-info/licenses/LICENSE
loppers-2.3.0.dist-info/RECORD
