Metadata-Version: 2.4
Name: loppers
Version: 2.3.0
Summary: Extract source file skeletons using tree-sitter queries
Project-URL: Homepage, https://github.com/undo76/loppers
Project-URL: Documentation, https://github.com/undo76/loppers#readme
Project-URL: Repository, https://github.com/undo76/loppers
Project-URL: Issues, https://github.com/undo76/loppers/issues
Author-email: Your Name <manolo.santos@gmail.com>
License: MIT
License-File: LICENSE
Keywords: ast,code-skeleton,extraction,loppers,parsing,tree-sitter
Classifier: Development Status :: 3 - Alpha
Classifier: Intended Audience :: Developers
Classifier: License :: OSI Approved :: MIT License
Classifier: Programming Language :: Python :: 3
Classifier: Programming Language :: Python :: 3.10
Classifier: Programming Language :: Python :: 3.11
Classifier: Programming Language :: Python :: 3.12
Classifier: Topic :: Software Development :: Code Generators
Classifier: Topic :: Software Development :: Libraries :: Python Modules
Requires-Python: >=3.10
Requires-Dist: binaryornot>=0.4.4
Requires-Dist: pathspec>=0.12.1
Requires-Dist: tree-sitter-language-pack>=0.10.0
Requires-Dist: tree-sitter>=0.25.0
Provides-Extra: dev
Requires-Dist: pytest-cov>=4.0.0; extra == 'dev'
Requires-Dist: pytest>=7.0.0; extra == 'dev'
Requires-Dist: ruff>=0.1.0; extra == 'dev'
